netboy/__init__.py
netboy/netboy.py
netboy/netboy2.py
netboy/aio_http/__init__.py
netboy/aio_http/aiohttp_factory.py
netboy/aio_http/aiohttp_handler.py
netboy/base/__init__.py
netboy/base/base_factory.py
netboy/celery/__init__.py
netboy/celery/app.py
netboy/celery/cli.py
netboy/celery/cmd.py
netboy/celery/tasks.py
netboy/multi_pycurl/__init__.py
netboy/multi_pycurl/curl_factory.py
netboy/multi_pycurl/curl_one.py
netboy/multi_pycurl/curl_result.py
netboy/multi_pycurl/curl_setup.py
netboy/multi_pycurl/multicurl_handler.py
netboy/remote/__init__.py
netboy/remote/auth.py
netboy/remote/run.py
netboy/selenium_chrome/__init__.py
netboy/selenium_chrome/chrome_driver_handler.py
netboy/selenium_chrome/chrome_factory.py
netboy/selenium_chrome/chrome_result.py
netboy/support/__init__.py
netboy/support/analysers.py
netboy/support/triggers.py
netboy/util/__init__.py
netboy/util/aop_wrapper.py
netboy/util/caoe.py
netboy/util/data_info.py
netboy/util/grouper.py
netboy/util/loader.py
netboy/util/makeup.py
netboy/util/payload.py
netboy/util/setup_log.py
netboy/util/soup.py
netboy-2018.8.7.data/data/bin/chromedriver
netboy-2018.8.7.dist-info/METADATA
netboy-2018.8.7.dist-info/RECORD
netboy-2018.8.7.dist-info/WHEEL
netboy-2018.8.7.dist-info/top_level.txt
