Metadata-Version: 2.1
Name: netboy
Version: 2018.8.7
Summary: the boy for net
Home-page: https://github.com/pingf/netboy2.git
Author: Jesse MENG
Author-email: pingf0@gmail.com
License: BSD
Platform: any
Classifier: Intended Audience :: Developers
Classifier: License :: OSI Approved :: BSD License
Classifier: Operating System :: OS Independent
Classifier: Programming Language :: Python
Classifier: Topic :: Software Development :: Libraries :: Python Modules
Requires-Dist: termcc
Requires-Dist: loader
Requires-Dist: aiohttp
Requires-Dist: aiofiles
Requires-Dist: websockets
Requires-Dist: pony
Requires-Dist: terminaltables
Requires-Dist: logcc
Requires-Dist: celery
Requires-Dist: inquirer
Requires-Dist: selenium
Requires-Dist: pycurl
Requires-Dist: worker
Requires-Dist: wrap
Requires-Dist: redis
